MANIFEST.in
README.rst
setup.py
test.py
docs/CREDITS.txt
docs/HISTORY.rst
docs/LICENSE.txt
docs/SAFELIST.rst
src/roughrider/__init__.py
src/roughrider.cors.egg-info/PKG-INFO
src/roughrider.cors.egg-info/SOURCES.txt
src/roughrider.cors.egg-info/dependency_links.txt
src/roughrider.cors.egg-info/namespace_packages.txt
src/roughrider.cors.egg-info/not-zip-safe
src/roughrider.cors.egg-info/requires.txt
src/roughrider.cors.egg-info/top_level.txt
src/roughrider/cors/__init__.py
src/roughrider/cors/policy.py
tests/test_policy.py
tests/test_preflight.py